README.md
setup.py
celerystar/__init__.py
celerystar/celerystar.py
celerystar.egg-info/PKG-INFO
celerystar.egg-info/SOURCES.txt
celerystar.egg-info/dependency_links.txt
celerystar.egg-info/requires.txt
celerystar.egg-info/top_level.txt
celerystar/static/favicon-16x16.png
celerystar/static/favicon-32x32.png
celerystar/static/index.html
celerystar/static/oauth2-redirect.html
celerystar/static/swagger-ui-bundle.js
celerystar/static/swagger-ui-bundle.js.map
celerystar/static/swagger-ui-standalone-preset.js
celerystar/static/swagger-ui-standalone-preset.js.map
celerystar/static/swagger-ui.css
celerystar/static/swagger-ui.css.map
celerystar/static/swagger-ui.js
celerystar/static/swagger-ui.js.map
celerystar_apistar/__init__.py
celerystar_apistar/compat.py
celerystar_apistar/conneg.py
celerystar_apistar/document.py
celerystar_apistar/exceptions.py
celerystar_apistar/formats.py
celerystar_apistar/http.py
celerystar_apistar/test.py
celerystar_apistar/types.py
celerystar_apistar/utils.py
celerystar_apistar/validators.py
celerystar_apistar/client/__init__.py
celerystar_apistar/client/auth.py
celerystar_apistar/client/client.py
celerystar_apistar/client/transports.py
celerystar_apistar/client/utils.py
celerystar_apistar/codecs/__init__.py
celerystar_apistar/codecs/base.py
celerystar_apistar/codecs/download.py
celerystar_apistar/codecs/jsondata.py
celerystar_apistar/codecs/jsonschema.py
celerystar_apistar/codecs/openapi.py
celerystar_apistar/codecs/text.py
celerystar_apistar/server/__init__.py
celerystar_apistar/server/adapters.py
celerystar_apistar/server/app.py
celerystar_apistar/server/asgi.py
celerystar_apistar/server/components.py
celerystar_apistar/server/core.py
celerystar_apistar/server/handlers.py
celerystar_apistar/server/injector.py
celerystar_apistar/server/router.py
celerystar_apistar/server/staticfiles.py
celerystar_apistar/server/templates.py
celerystar_apistar/server/validation.py
celerystar_apistar/server/wsgi.py