Metadata-Version: 1.1
Name: celerystar
Version: 0.0.2
Summary: Celery based task framework with dependency injection
Home-page: http://gerenciagram.com.br
Author: ['Pedro Lacerda', 'Tassio Guimarães']
Author-email: pslacerda+dev@gmail.com
License: MIT
Platform: UNKNOWN
Classifier: Development Status :: 3 - Alpha
Classifier: Intended Audience :: Developers
Classifier: License :: OSI Approved :: MIT License
Classifier: Topic :: System :: Networking
Classifier: Programming Language :: Python :: 3.6
